simple_user_auth/README.md
simple_user_auth/__init__.py
simple_user_auth/const.cp37-win_amd64.pyd
simple_user_auth/init.cp37-win_amd64.pyd
simple_user_auth-0.0.2.dist-info/METADATA
simple_user_auth-0.0.2.dist-info/WHEEL
simple_user_auth-0.0.2.dist-info/top_level.txt
simple_user_auth-0.0.2.dist-info/RECORD
