Metadata-Version: 2.1
Name: simple-user-auth
Version: 0.0.2
Summary: simple user management and authorization system
Home-page: UNKNOWN
Author: spectereye
Author-email: spectereye@gmail.com
License: UNKNOWN
Platform: UNKNOWN
Requires-Python: >=3.7
